oauth_clients/__init__.py
oauth_clients/admin.py
oauth_clients/apps.py
oauth_clients/models.py
oauth_clients/urls.py
oauth_clients/views.py
oauth_clients/migrations/0001_initial.py
oauth_clients/migrations/0002_client_scope.py
oauth_clients/migrations/0003_auto_20181126_2148.py
oauth_clients/migrations/0004_auto_20181127_0314.py
oauth_clients/migrations/__init__.py
oauth_clients/static/css/oauth_clients.css
oauth_clients/static/js/oauth_clients.js
oauth_clients/templates/admin/oauth_clients/client/change_form.html
oauth_clients/templates/oauth_clients/base.html
dj_oauth_clients-0.1.0.dist-info/AUTHORS.rst
dj_oauth_clients-0.1.0.dist-info/LICENSE
dj_oauth_clients-0.1.0.dist-info/METADATA
dj_oauth_clients-0.1.0.dist-info/WHEEL
dj_oauth_clients-0.1.0.dist-info/top_level.txt
dj_oauth_clients-0.1.0.dist-info/RECORD
