Metadata-Version: 2.1
Name: dj-oauth-clients
Version: 0.1.0
Summary: Django app for handling oauth2 clients.
Home-page: https://github.com/kverdecia/dj-oauth-clients
Author: Karel Antonio Verdecia Ortiz
Author-email: kverdecia@gmail.com
License: MIT
Keywords: dj-oauth-clients
Platform: UNKNOWN
Classifier: Development Status :: 3 - Alpha
Classifier: Framework :: Django :: 1.11
Classifier: Framework :: Django :: 2.0
Classifier: Intended Audience :: Developers
Classifier: License :: OSI Approved :: BSD License
Classifier: Natural Language :: English
Classifier: Programming Language :: Python :: 2
Classifier: Programming Language :: Python :: 2.7
Classifier: Programming Language :: Python :: 3
Classifier: Programming Language :: Python :: 3.4
Classifier: Programming Language :: Python :: 3.5
Classifier: Programming Language :: Python :: 3.6
Requires-Dist: django-model-utils (>=2.0)
